ose_plugin_hierarchical_spreadsheets/GenerateHierarchicalSpreadsheetReleaseStep.py
ose_plugin_hierarchical_spreadsheets/__init__.py
ose_plugin_hierarchical_spreadsheets-0.3.0.dist-info/METADATA
ose_plugin_hierarchical_spreadsheets-0.3.0.dist-info/WHEEL
ose_plugin_hierarchical_spreadsheets-0.3.0.dist-info/entry_points.txt
ose_plugin_hierarchical_spreadsheets-0.3.0.dist-info/top_level.txt
ose_plugin_hierarchical_spreadsheets-0.3.0.dist-info/RECORD
