Metadata-Version: 2.4
Name: ose-plugin-hierarchical-spreadsheets
Version: 0.3.0
Summary: OntoSpreadEd plugin for hierarchical spreadsheet generation
Requires-Python: >=3.12
Requires-Dist: ose-core==0.3.0
